collegelistscrapper/__init__.py
collegelistscrapper/__main__.py
collegelistscrapper/nichescrapper.py
collegelistscrapper-2.0.0.dist-info/METADATA
collegelistscrapper-2.0.0.dist-info/WHEEL
collegelistscrapper-2.0.0.dist-info/top_level.txt
collegelistscrapper-2.0.0.dist-info/RECORD
